idemux/__init__.py
idemux/__main__.py
idemux/_version.py
idemux/idemux.py
idemux/ioutils/__init__.py
idemux/ioutils/barcode.py
idemux/ioutils/file_handler.py
idemux/ioutils/parser.py
idemux/ioutils/writer.py
idemux/processing/__init__.py
idemux/processing/demuxer.py
idemux/resources/__init__.py
idemux/resources/barcodes/__init__.py
idemux/resources/barcodes/i1/__init__.py
idemux/resources/barcodes/i1/base_mapping_b384_l10.tsv
idemux/resources/barcodes/i1/base_mapping_b384_l12.tsv
idemux/resources/barcodes/i1/base_mapping_b96_l10.tsv
idemux/resources/barcodes/i1/base_mapping_b96_l12.tsv
idemux/resources/barcodes/i1/base_mapping_b96_l8.tsv
idemux/resources/barcodes/i5/__init__.py
idemux/resources/barcodes/i5/base_mapping_b384_l10.tsv
idemux/resources/barcodes/i5/base_mapping_b384_l12.tsv
idemux/resources/barcodes/i5/base_mapping_b96_l10.tsv
idemux/resources/barcodes/i5/base_mapping_b96_l12.tsv
idemux/resources/barcodes/i5/base_mapping_b96_l8.tsv
idemux/resources/barcodes/i5_rc/__init__.py
idemux/resources/barcodes/i5_rc/base_mapping_b384_l10.tsv
idemux/resources/barcodes/i5_rc/base_mapping_b384_l12.tsv
idemux/resources/barcodes/i5_rc/base_mapping_b96_l10.tsv
idemux/resources/barcodes/i5_rc/base_mapping_b96_l12.tsv
idemux/resources/barcodes/i5_rc/base_mapping_b96_l8.tsv
idemux/resources/barcodes/i7/__init__.py
idemux/resources/barcodes/i7/base_mapping_b384_l10.tsv
idemux/resources/barcodes/i7/base_mapping_b384_l12.tsv
idemux/resources/barcodes/i7/base_mapping_b96_l10.tsv
idemux/resources/barcodes/i7/base_mapping_b96_l12.tsv
idemux/resources/barcodes/i7/base_mapping_b96_l8.tsv
idemux-0.1.6.dist-info/AUTHORS.rst
idemux-0.1.6.dist-info/LICENCE
idemux-0.1.6.dist-info/METADATA
idemux-0.1.6.dist-info/WHEEL
idemux-0.1.6.dist-info/entry_points.txt
idemux-0.1.6.dist-info/top_level.txt
idemux-0.1.6.dist-info/RECORD
