Metadata-Version: 2.1
Name: idemux
Version: 0.1.6
Summary: A Lexogen tool for demultiplexing and  index error correcting fastq files. Works with Lexogen i7, i5 and i1 barcodes.
Home-page: https://github.com/lexogen-tools/idemux
Author: Falko Hofmann, Michael Moldaschl, Andreas Tuerk
Author-email: falko.hofmann@lexogen.com, michael.moldaschl@lexogen.com, andreas.tuerk@lexogen.com
License: UNKNOWN
Keywords: idemux
Platform: UNKNOWN
Classifier: Development Status :: 4 - Beta
Classifier: Intended Audience :: Science/Research
Classifier: Topic :: Scientific/Engineering :: Bio-Informatics
Classifier: Natural Language :: English
Classifier: Programming Language :: Python :: 3
Classifier: Programming Language :: Python :: 3.6
Classifier: Programming Language :: Python :: 3.7
Classifier: Programming Language :: Python :: 3.8
Classifier: Programming Language :: Python :: 3.9
Requires-Python: >=3.6
Requires-Dist: tqdm
Requires-Dist: importlib-resources ; python_version < "3.7"
Requires-Dist: dataclasses ; python_version < "3.7"
Provides-Extra: dev
Requires-Dist: pytest ; extra == 'dev'
Requires-Dist: pytest-cov ; extra == 'dev'
Requires-Dist: coverage ; extra == 'dev'
Provides-Extra: docs
Requires-Dist: sphinx ; extra == 'docs'
